MANIFEST.in
README.rst
setup.py
collective/__init__.py
collective.js.fullcalendar.egg-info/PKG-INFO
collective.js.fullcalendar.egg-info/SOURCES.txt
collective.js.fullcalendar.egg-info/dependency_links.txt
collective.js.fullcalendar.egg-info/entry_points.txt
collective.js.fullcalendar.egg-info/namespace_packages.txt
collective.js.fullcalendar.egg-info/not-zip-safe
collective.js.fullcalendar.egg-info/requires.txt
collective.js.fullcalendar.egg-info/top_level.txt
collective/js/__init__.py
collective/js/fullcalendar/__init__.py
collective/js/fullcalendar/configure.zcml
collective/js/fullcalendar/tests.py
collective/js/fullcalendar/upgrades.py
collective/js/fullcalendar/version.txt
collective/js/fullcalendar/profiles/plone4/cssregistry.xml
collective/js/fullcalendar/profiles/plone4/jsregistry.xml
collective/js/fullcalendar/profiles/plone4/metadata.xml
collective/js/fullcalendar/profiles/plone5/metadata.xml
collective/js/fullcalendar/profiles/plone5/registry.xml
collective/js/fullcalendar/profiles/uninstall-plone4/cssregistry.xml
collective/js/fullcalendar/profiles/uninstall-plone4/jsregistry.xml
collective/js/fullcalendar/profiles/uninstall-plone5/registry.xml
collective/js/fullcalendar/resources/fullcalendar.css
collective/js/fullcalendar/resources/fullcalendar.gcal.js
collective/js/fullcalendar/resources/fullcalendar.min.js
collective/js/fullcalendar/resources/fullcalendar.plone5.print.css
collective/js/fullcalendar/resources/fullcalendar.print.css
docs/HISTORY.txt
docs/INSTALL.txt
docs/LICENSE.GPL
docs/LICENSE.txt