Metadata-Version: 1.1
Name: collective.js.fullcalendar
Version: 1.6.5
Summary: Plone package for integrating fullcalendar JS
Home-page: https://github.com/collective/collective.js.fullcalendar
Author: Simone Orsi
Author-email: simahawk@gmail.com
License: GPL
Keywords: Plone JQuery Javascript Fullcalendar
Platform: UNKNOWN
Classifier: Framework :: Plone
Classifier: Programming Language :: Python
Classifier: Intended Audience :: Developers
Classifier: Intended Audience :: End Users/Desktop
Classifier: Topic :: Software Development :: Libraries :: Python Modules
Classifier: License :: OSI Approved :: GNU General Public License (GPL)
